{"train/rewards/diversity_reward_fn/std":0.22498854994773865,"rewards/diversity_reward/std":0.22498854994773865,"profiling/Time taken: UnslothGRPOTrainer._calculate_rewards":0.15752264000184368,"rewards/pnl_reward/mean":-0.08648849502205849,"train/clip_ratio/low_min":0,"story/pnl_std":1.0187833273942826,"train/rewards/diversity_reward_fn/mean":-0.48250000178813934,"rewards/news_alpha_reward/std":0,"train/global_step":50,"profiling/Time taken: UnslothGRPOTrainer.risk_reward_fn":9.697499626781791e-05,"train/clip_ratio/high_mean":0,"train/completions/clipped_ratio":0.45,"train/reward":0.28101147413253785,"story/format_mean":0.85,"train/grad_norm":0.4336891770362854,"train/kl":0.0192789162741974,"story/global_step":50,"profiling/Time taken: UnslothGRPOTrainer.diversity_reward_fn":0.00010184399434365332,"train/rewards/risk_reward_fn/mean":0,"train/completions/max_length":512,"train/frac_reward_zero_std":0,"rewards/news_alpha_reward/mean":0,"train/rewards/news_alpha_reward_fn/mean":0,"story/diversity_std":0.4284492385335747,"story/risk_std":0,"train/epoch":0.3333333333333333,"train/learning_rate":1.1111111111111112e-06,"rewards/oversight_reward/std":0,"story/oversight_mean":0,"rewards/format_reward/mean":0.85,"_wandb":{"runtime":1430},"train/rewards/pnl_reward_fn/std":0.13522273674607277,"train/rewards/risk_reward_fn/std":0,"train/rewards/format_reward_fn/std":0.3,"reward":0.28101147413253785,"story/phase":"Act IV: The Watcher Awakens","train/completions/max_terminated_length":260.4,"story/oversight_std":0,"profiling/Time taken: UnslothGRPOTrainer.oversight_reward_fn":8.5624007624574e-05,"train/completions/min_length":97.2,"profiling/Time taken: UnslothGRPOTrainer.news_alpha_reward_fn":9.48450033320114e-05,"train/num_tokens":209774,"profiling/Time taken: UnslothGRPOTrainer._prepare_inputs":3.130000550299883e-06,"train/completions/mean_terminated_length":173.36666870117188,"rl_agents":5,"train_steps_per_second":0.035,"train/rewards/format_reward_fn/mean":0.85,"train/clip_ratio/low_mean":0,"rewards/format_reward/std":0.3,"train/clip_ratio/region_mean":0,"agent_count":6,"reward_std":0.4974463604390621,"_step":524,"_timestamp":1.7771751151917102e+09,"frac_reward_zero_std":0,"train_loss":0.010303336977958679,"train/clip_ratio/high_max":0,"train/reward_std":0.4974463604390621,"train/loss":0.147719669342041,"train/completion_length":326.25,"train/completions/mean_length":326.25,"_runtime":1430,"profiling/Time taken: UnslothGRPOTrainer.transformers.generate":24.565723813007935,"rewards/risk_reward/mean":0,"rewards/risk_reward/std":0,"profiling/Time taken: UnslothGRPOTrainer.format_reward_fn":0.15517827500298154,"rewards/pnl_reward/std":0.13522273674607277,"train/rewards/oversight_reward_fn/mean":0,"scripted_agents":1,"story/format_std":0.6538348415311012,"rewards/oversight_reward/mean":0,"train/completions/min_terminated_length":97.2,"total_episodes":30,"total_flos":0,"train/rewards/news_alpha_reward_fn/std":0,"total_training_steps":50,"story/news_alpha_std":0,"story/pnl_mean":-0.08648849561582013,"train/rewards/pnl_reward_fn/mean":-0.08648849502205849,"train/rewards/oversight_reward_fn/std":0,"story/risk_mean":0,"story/news_alpha_mean":0,"rewards/diversity_reward/mean":-0.48250000178813934,"train_samples_per_second":0.142,"train_runtime":1408.6483,"story/diversity_mean":-0.48249999999999993,"profiling/Time taken: UnslothGRPOTrainer.pnl_reward_fn":8.909500320442021e-05}